microblog/__init__.py
microblog/admin.py
microblog/apps.py
microblog/fixtures/categories.json
microblog/fixtures/posts.json
microblog/managers.py
microblog/migrations/0001_initial.py
microblog/migrations/0002_add_weight.py
microblog/migrations/0003_alter_weight_default.py
microblog/migrations/__init__.py
microblog/models.py
microblog/urls.py
microblog/views.py
django_microblog-0.1.2.dist-info/LICENSE
django_microblog-0.1.2.dist-info/WHEEL
django_microblog-0.1.2.dist-info/METADATA
django_microblog-0.1.2.dist-info/RECORD
