Metadata-Version: 2.1
Name: django-microblog
Version: 0.1.2
Summary: Simple blogging application for Django
Home-page: https://github.com/lukasvinclav/django-microblog
License: MIT
Keywords: django,blog,post,category
Requires-Python: >=3.6,<4.0
Classifier: Environment :: Web Environment
Classifier: Framework :: Django
Classifier: Intended Audience :: Developers
Classifier: License :: OSI Approved :: MIT License
Classifier: Operating System :: OS Independent
Classifier: Programming Language :: Python
Classifier: Programming Language :: Python :: 3
Classifier: Programming Language :: Python :: 3.6
Classifier: Programming Language :: Python :: 3.7
Classifier: Programming Language :: Python :: 3.8
Requires-Dist: django (>=3.0,<4.0)
Requires-Dist: pillow (>=7.0,<8.0)
Project-URL: Repository, https://github.com/lukasvinclav/django-microblog
